setup.py
xmind_to_testlink/__init__.py
xmind_to_testlink/check_xmind.py
xmind_to_testlink/chipcase_restructure.py
xmind_to_testlink/dict_to_json.py
xmind_to_testlink/dict_to_xml.py
xmind_to_testlink/libtestlinkxml.py
xmind_to_testlink/main.py
xmind_to_testlink/markdown_to_dict.py
xmind_to_testlink/preprocess.py
xmind_to_testlink/read_xml.py
xmind_to_testlink/req_analyse.py
xmind_to_testlink/req_rexmind.py
xmind_to_testlink/req_xmind_to_dict.py
xmind_to_testlink/rexmind.py
xmind_to_testlink/xmind_to_dict.py
xmind_to_testlink/xml_update.py
xmind_to_testlink/zip_need.py
xmind_to_testlink.egg-info/PKG-INFO
xmind_to_testlink.egg-info/SOURCES.txt
xmind_to_testlink.egg-info/dependency_links.txt
xmind_to_testlink.egg-info/entry_points.txt
xmind_to_testlink.egg-info/top_level.txt