Metadata-Version: 1.0
Name: xmind-to-testlink
Version: 2.0.3
Summary: Convert xmindzen to TestLink xml
Home-page: UNKNOWN
Author: zhaobk
Author-email: zhaobk@nationalchip.com
License: UNKNOWN
Keywords: xmind testlink import converter testing testcase requirement
Platform: UNKNOWN
